README.md
setup.py
simpleyt/__init__.py
simpleyt/comment.py
simpleyt/exception.py
simpleyt/playlist.py
simpleyt/video_comment.py
simpleyt/youtube_api.py
simpleyt/youtube_channel.py
simpleyt/youtube_video.py
simpleyt.egg-info/PKG-INFO
simpleyt.egg-info/SOURCES.txt
simpleyt.egg-info/dependency_links.txt
simpleyt.egg-info/not-zip-safe
simpleyt.egg-info/requires.txt
simpleyt.egg-info/top_level.txt