Metadata-Version: 2.1
Name: simpleyt
Version: 1.1
Summary: A Simple Wrapper for Yotube Data Api v3 for Python which helps querying the public Youtube Data in a hassle free way
Home-page: https://github.com/VarthanV/simple-yt
Author: Vishnu Varthan Rao
Author-email: vishnulatha006@gmail.com
License: MIT License
Keywords: youtube,youtubeapi,youtube data,youtubevideo,youtube playlists,youtube channel,python youtube,youtube,ytd
Platform: UNKNOWN
Classifier: Intended Audience :: Developers
Classifier: License :: OSI Approved :: MIT License
Classifier: Programming Language :: Python :: 3
Classifier: Programming Language :: Python :: 3.3
Classifier: Operating System :: OS Independent
Classifier: Topic :: Software Development :: Libraries
Classifier: Topic :: Utilities
